pbatoolkit_gpu-0.0.3.dist-info/METADATA
pbatoolkit_gpu-0.0.3.dist-info/WHEEL
pbatoolkit_gpu-0.0.3.dist-info/RECORD
lib64/libPhysicsBasedAnimationToolkit.a
lib64/libTracyClient.a
lib64/cmake/PhysicsBasedAnimationToolkit/PhysicsBasedAnimationToolkit_Targets-release.cmake
lib64/cmake/PhysicsBasedAnimationToolkit/PhysicsBasedAnimationToolkit_Targets.cmake
lib64/cmake/PhysicsBasedAnimationToolkit/PhysicsBasedAnimationToolkitConfig.cmake
pbatoolkit/gpu.py
pbatoolkit/libPhysicsBasedAnimationToolkit.a
pbatoolkit/sim.py
pbatoolkit/profiling.py
pbatoolkit/_pbat.cpython-311-x86_64-linux-gnu.so
pbatoolkit/geometry.py
pbatoolkit/__init__.py
pbatoolkit/libTracyClient.a
pbatoolkit/fem.py
pbatoolkit/math/__init__.py
pbatoolkit/math/linalg/__init__.py
